README.md
setup.py
interactiongrader/Answer.py
interactiongrader/Changetype.py
interactiongrader/Phonemes.py
interactiongrader/__init__.py
interactiongrader.egg-info/PKG-INFO
interactiongrader.egg-info/SOURCES.txt
interactiongrader.egg-info/dependency_links.txt
interactiongrader.egg-info/top_level.txt