Metadata-Version: 2.1
Name: interactiongrader
Version: 0.0.5
Summary: Grade free form text answers
Home-page: https://github.com/pypa/sampleproject
Author: Daniel Brandt
Author-email: dbbrandt@gmail.com
License: UNKNOWN
Platform: UNKNOWN
Classifier: Programming Language :: Python :: 3
Classifier: License :: OSI Approved :: MIT License
Classifier: Operating System :: OS Independent
